zeroconnect/__about__.py
zeroconnect/__init__.py
zeroconnect/client.py
zeroconnect/logging.py
zeroconnect/message_socket.py
zeroconnect/server.py
zeroconnect/zcat.py
zeroconnect/zeroconnect.py
zeroconnect/utils/filter_map.py
zeroconnect/utils/waitgroup.py
zeroconnect-1.0.1.dist-info/METADATA
zeroconnect-1.0.1.dist-info/WHEEL
zeroconnect-1.0.1.dist-info/licenses/LICENSE.txt
zeroconnect-1.0.1.dist-info/RECORD
