Metadata-Version: 2.1
Name: zeroconnect
Version: 1.0.1
Summary: Use zeroconf to automatically connect devices via TCP on a LAN
Project-URL: Documentation, https://github.com/erhannis/zeroconnect#readme
Project-URL: Issues, https://github.com/erhannis/zeroconnect/issues
Project-URL: Source, https://github.com/erhannis/zeroconnect
Author-email: Erhannis Kirran <eyeillus@gmail.com>
License-File: LICENSE.txt
Keywords: automagic,automatic,connect,iot,mesh,network,tcp,zeroconf
Classifier: Development Status :: 4 - Beta
Classifier: Programming Language :: Python
Classifier: Programming Language :: Python :: 3.7
Classifier: Programming Language :: Python :: 3.8
Classifier: Programming Language :: Python :: 3.9
Classifier: Programming Language :: Python :: 3.10
Classifier: Programming Language :: Python :: 3.11
Classifier: Programming Language :: Python :: Implementation :: CPython
Classifier: Programming Language :: Python :: Implementation :: PyPy
Requires-Python: >=3.7
Requires-Dist: argparse
Requires-Dist: netifaces
Requires-Dist: zeroconf
